qwitch/__init__.py
qwitch/api.py
qwitch/config.py
qwitch/qwitch.py
qwitch-2.5.3.dist-info/licenses/LICENCE
qwitch-2.5.3.dist-info/METADATA
qwitch-2.5.3.dist-info/WHEEL
qwitch-2.5.3.dist-info/entry_points.txt
qwitch-2.5.3.dist-info/top_level.txt
qwitch-2.5.3.dist-info/RECORD
