Metadata-Version: 2.4
Name: qwitch
Version: 2.5.3
Summary: Stream twitch in Quicktime.
Author-email: Jean-Francois Vaduret <jean.francois.vaduret@gmail.com>
License-Expression: MIT
Project-URL: Source, https://github.com/gencys/qwitch
Project-URL: Tracker, https://github.com/gencys/qwitch/issues
Classifier: Development Status :: 5 - Production/Stable
Classifier: Environment :: Console
Classifier: Intended Audience :: End Users/Desktop
Classifier: Operating System :: MacOS
Classifier: Programming Language :: Python :: 3
Classifier: Programming Language :: Python :: 3 :: Only
Classifier: Programming Language :: Python :: 3.8
Classifier: Programming Language :: Python :: 3.9
Classifier: Programming Language :: Python :: 3.10
Classifier: Programming Language :: Python :: 3.11
Classifier: Topic :: Internet :: WWW/HTTP
Classifier: Topic :: Multimedia :: Sound/Audio
Classifier: Topic :: Multimedia :: Video
Classifier: Topic :: Utilities
Requires-Python: >=3.8
License-File: LICENCE
Requires-Dist: requests
Requires-Dist: streamlink
Dynamic: license-file
